{
  "schemaVersion": "mcp-021.machine-observations.boolean.v1",
  "nodeId": "fixture-node-mainline-d-001",
  "checkedRawKeys": [
    "asks_for_evidence",
    "provides_evidence",
    "evidence_supports_claim",
    "creates_source_chain_gap",
    "opens_evidence_debt_marker",
    "closes_evidence_debt_marker",
    "supplies_corroborating_document",
    "source_provided",
    "quote_provided",
    "concrete_example_requested",
    "concrete_example_provided",
    "evidence_claim_present",
    "evidence_gap_present",
    "source_chain_repair",
    "anecdote_used",
    "statistic_used",
    "external_authority_used",
    "evidence_quality_questioned",
    "burden_request_present",
    "names_method_difference",
    "separates_observation_from_inference",
    "flags_context_limit"
  ],
  "observations": {
    "asks_for_evidence": false,
    "provides_evidence": true,
    "evidence_supports_claim": false,
    "creates_source_chain_gap": false,
    "opens_evidence_debt_marker": false,
    "closes_evidence_debt_marker": false,
    "supplies_corroborating_document": false,
    "source_provided": true,
    "quote_provided": false,
    "concrete_example_requested": false,
    "concrete_example_provided": false,
    "evidence_claim_present": false,
    "evidence_gap_present": false,
    "source_chain_repair": false,
    "anecdote_used": false,
    "statistic_used": true,
    "external_authority_used": false,
    "evidence_quality_questioned": false,
    "burden_request_present": false,
    "names_method_difference": true,
    "separates_observation_from_inference": false,
    "flags_context_limit": false
  },
  "confidence": {
    "asks_for_evidence": "medium",
    "provides_evidence": "high",
    "evidence_supports_claim": "medium",
    "creates_source_chain_gap": "medium",
    "opens_evidence_debt_marker": "medium",
    "closes_evidence_debt_marker": "medium",
    "supplies_corroborating_document": "medium",
    "source_provided": "high",
    "quote_provided": "medium",
    "concrete_example_requested": "medium",
    "concrete_example_provided": "medium",
    "evidence_claim_present": "medium",
    "evidence_gap_present": "medium",
    "source_chain_repair": "medium",
    "anecdote_used": "medium",
    "statistic_used": "high",
    "external_authority_used": "medium",
    "evidence_quality_questioned": "medium",
    "burden_request_present": "medium",
    "names_method_difference": "medium",
    "separates_observation_from_inference": "medium",
    "flags_context_limit": "medium"
  },
  "evidenceSpan": {
    "asks_for_evidence": null,
    "provides_evidence": "Per the 2024 EPA report Table 3.1",
    "evidence_supports_claim": null,
    "creates_source_chain_gap": null,
    "opens_evidence_debt_marker": null,
    "closes_evidence_debt_marker": null,
    "supplies_corroborating_document": null,
    "source_provided": "2024 EPA report Table 3.1",
    "quote_provided": null,
    "concrete_example_requested": null,
    "concrete_example_provided": null,
    "evidence_claim_present": null,
    "evidence_gap_present": null,
    "source_chain_repair": null,
    "anecdote_used": null,
    "statistic_used": "40% drop in tailpipe emissions from 2020 to 2023",
    "external_authority_used": null,
    "evidence_quality_questioned": null,
    "burden_request_present": null,
    "names_method_difference": "administrative records",
    "separates_observation_from_inference": null,
    "flags_context_limit": null
  },
  "modelInfo": {
    "provider": "mcp",
    "serverName": "cdiscourse-mcp-server",
    "classifierSetVersion": "family-d-v1"
  }
}
